std_buffer/__init__.py
std_buffer/buffered_metadata_pb2.py
std_buffer/image_metadata_pb2.py
std_buffer/stream_binary.py
std_buffer/writer_command_pb2.py
std_buffer/eiger/__init__.py
std_buffer/eiger/data.py
std_buffer/eiger/std-daq_config_gen.py
std_buffer/eiger/udp_sim_eg.py
std_buffer/gigafrost/__init__.py
std_buffer/gigafrost/data.py
std_buffer/gigafrost/udp_sim_gf.py
std_buffer/jungfrau/__init__.py
std_buffer/jungfrau/data.py
std_buffer/jungfrau/extract_gains_and_pedestals_for_module.py
std_buffer/jungfrau/stream_binary_jf_sim.py
std_buffer/jungfrau/udp_sim_jf.py
std_buffer-0.13.14.dist-info/METADATA
std_buffer-0.13.14.dist-info/WHEEL
std_buffer-0.13.14.dist-info/top_level.txt
std_buffer-0.13.14.dist-info/RECORD
