Metadata-Version: 2.1
Name: std-buffer
Version: 0.13.14
Summary: Standard DAQ buffer interface
Home-page: UNKNOWN
Author: Paul Scherrer Institute
Author-email: daq@psi.ch
Maintainer: Paul Scherrer Institute
Maintainer-email: daq@psi.ch
License: GPL3
Platform: UNKNOWN
